{
  "mode_income_selected": "Вы выбрали режим 'Увеличить доход'. Отличный выбор! Я помогу тебе найти новые источники дохода или оптимизировать текущие.",
  "mode_position_selected": "Вы выбрали режим 'Карьерный рост / Новая работа'. Поехали! Мы разработаем план для твоего профессионального развития.",
  "mode_orientation_selected": "Вы выбрали режим 'Профориентация'. Замечательно! Вместе мы определим профессию, которая максимально соответствует твоим способностям и интересам.",
  "unknown_mode_selected": "Произошла ошибка при выборе режима. Пожалуйста, попробуйте еще раз.",
  "back_to_main_menu_message": "Вы вернулись в главное меню. Что будем делать дальше?",
  "something_went_wrong": "Что-то пошло не так. Пожалуйста, попробуйте снова."
}